MANIFEST.in
setup.py
demo_app/__init__.py
demo_app/admin.py
demo_app/extension.py
demo_app/models.py
demo_app/tests.py
demo_app/urls.py
demo_app/views.py
demo_app/templates/demo_app/hello.html
lava_server_demo.egg-info/PKG-INFO
lava_server_demo.egg-info/SOURCES.txt
lava_server_demo.egg-info/dependency_links.txt
lava_server_demo.egg-info/entry_points.txt
lava_server_demo.egg-info/not-zip-safe
lava_server_demo.egg-info/requires.txt
lava_server_demo.egg-info/top_level.txt