Metadata-Version: 1.0
Name: lava-server-demo
Version: 1.0
Summary: Demo application for LAVA Server
Home-page: UNKNOWN
Author: Zygmunt Krynicki
Author-email: zygmunt.krynicki@linaro.org
License: AGPL
Platform: UNKNOWN
